{"is_source_file": true, "format": "TypeScript with JSX (TSX)", "description": "This file defines an authentication gate component for a React application, providing sign-in and registration interfaces with form handling and state management.", "external_files": ["./AuthContext"], "external_methods": ["useAuth.login", "useAuth.register"], "published": [], "classes": [], "methods": [{"name": "AuthGateScreen", "description": "Main component that toggles between Sign In and Register screens."}, {"name": "LoginScreen", "description": "Component for the user to input email and password to sign in."}, {"name": "RegisterScreen", "description": "Component for the user to input email and password to register."}], "calls": ["useAuth.login", "useAuth.register"], "search-terms": ["AuthGateScreen", "LoginScreen", "RegisterScreen", "useAuth", "sign-in", "register", "auth gate", "auth component", "TypeScript React auth", "TSX login register"], "state": 2, "file_id": 16, "knowledge_revision": 46, "git_revision": "", "revision_history": [{"35": ""}, {"46": ""}], "ctags": [], "hash": "c51bd334e11ff2e6ce0de758e721cd9e", "format-version": 4, "code-base-name": "todo_frontend", "filename": "todo_frontend/src/app/auth/AuthGateScreen.tsx"}